hyperer/__init__.py
hyperer/cargo.py
hyperer/rg.py
hyperer/ruff.py
hyperer-0.3.0.dist-info/LICENSE
hyperer-0.3.0.dist-info/METADATA
hyperer-0.3.0.dist-info/WHEEL
hyperer-0.3.0.dist-info/entry_points.txt
hyperer-0.3.0.dist-info/RECORD
