Metadata-Version: 2.1
Name: hyperer
Version: 0.3.0
Summary: Injects hyperlinks into terminal commands
Home-page: https://github.com/groves/hyperer
Author: Charlie Groves
Author-email: c@sevorg.org
Requires-Python: >=3.9,<4.0
Classifier: Programming Language :: Python :: 3
Classifier: Programming Language :: Python :: 3.9
Classifier: Programming Language :: Python :: 3.10
Classifier: Programming Language :: Python :: 3.11
Project-URL: Repository, https://github.com/groves/hyperer
